bitbucket_code_reviewer/__init__.py
bitbucket_code_reviewer/bitbucket/__init__.py
bitbucket_code_reviewer/bitbucket/client.py
bitbucket_code_reviewer/core/__init__.py
bitbucket_code_reviewer/core/config.py
bitbucket_code_reviewer/core/diff_utils.py
bitbucket_code_reviewer/core/logger.py
bitbucket_code_reviewer/core/models.py
bitbucket_code_reviewer/llm/__init__.py
bitbucket_code_reviewer/llm/agent.py
bitbucket_code_reviewer/llm/callbacks.py
bitbucket_code_reviewer/llm/providers.py
bitbucket_code_reviewer/llm/tools/__init__.py
bitbucket_code_reviewer/llm/tools/_shared.py
bitbucket_code_reviewer/llm/tools/get_file_info.py
bitbucket_code_reviewer/llm/tools/list_directory.py
bitbucket_code_reviewer/llm/tools/read_diff.py
bitbucket_code_reviewer/llm/tools/read_file.py
bitbucket_code_reviewer/llm/tools/search_files.py
bitbucket_code_reviewer/llm/tools/speak.py
bitbucket_code_reviewer/llm/tools/submit_review.py
bitbucket_code_reviewer/main.py
bitbucket_code_reviewer/prompts/__init__.py
bitbucket_code_reviewer/prompts/system/identity.md
bitbucket_code_reviewer/prompts/system/tools.md
bitbucket_code_reviewer/prompts/system/workflow.md
bitbucket_code_reviewer/prompts/user/templates/initial_message.j2
bitbucket_code_reviewer/prompts/user/templates/retry_feedback.j2
bitbucket_code_reviewer/prompts/user/templates/sections/file_path_list.j2
bitbucket_code_reviewer/prompts/user/templates/sections/json_requirements.j2
bitbucket_code_reviewer/prompts/user/templates/sections/pr_context.j2
bitbucket_code_reviewer/prompts/user/templates/sections/previous_comments.j2
bitbucket_code_reviewer/reviewer/__init__.py
bitbucket_code_reviewer/reviewer/output_formatter.py
bitbucket_code_reviewer/reviewer/review_orchestrator.py
bitbucket_code_reviewer-0.2.9.dist-info/METADATA
bitbucket_code_reviewer-0.2.9.dist-info/WHEEL
bitbucket_code_reviewer-0.2.9.dist-info/entry_points.txt
bitbucket_code_reviewer-0.2.9.dist-info/licenses/LICENSE
bitbucket_code_reviewer-0.2.9.dist-info/RECORD
