Metadata-Version: 2.4
Name: bitbucket-code-reviewer
Version: 0.2.9
Summary: Bitbucket Code Reviewer CLI Tool
License-File: LICENSE
Author: kilsbo
Author-email: kilsbo@example.com
Requires-Python: >=3.10,<4.0
Classifier: Programming Language :: Python :: 3
Classifier: Programming Language :: Python :: 3.10
Classifier: Programming Language :: Python :: 3.11
Classifier: Programming Language :: Python :: 3.12
Classifier: Programming Language :: Python :: 3.13
Classifier: Programming Language :: Python :: 3.14
Requires-Dist: click (>=8.1.0,<9.0.0)
Requires-Dist: colorama (>=0.4.6,<0.5.0)
Requires-Dist: httpx (>=0.25.0,<0.28.0)
Requires-Dist: jinja2 (>=3.1.0,<4.0.0)
Requires-Dist: langchain (>=0.3.27,<0.4.0)
Requires-Dist: langchain-community (>=0.3.27,<0.4.0)
Requires-Dist: langchain-openai (>=0.3.35,<0.4.0)
Requires-Dist: packaging (>=23.2,<24.0)
Requires-Dist: pydantic (>=2.0.0,<3.0.0)
Requires-Dist: pydantic-settings (>=2.0.0,<3.0.0)
Requires-Dist: requests (>=2.31.0,<3.0.0)
